[{"created_at":"2013-02-11T10:57:13Z","description":null,"foursquare_icon":null,"foursquare_id":null,"group":"tosee","icon_content_type":null,"icon_file_name":null,"icon_file_size":null,"icon_update_at":null,"id":1,"is_route":null,"name":"Cataratas","name_en":null,"name_eu":null,"slug":null,"supercategory_id":1,"updated_at":"2013-02-11T10:57:13Z","icon_urls":{"small":"/icons/small/missing.png","med":"/icons/med/missing.png","big":"/icons/big/missing.png"}},{"created_at":"2013-02-11T10:57:13Z","description":null,"foursquare_icon":null,"foursquare_id":null,"group":"tosee","icon_content_type":null,"icon_file_name":null,"icon_file_size":null,"icon_update_at":null,"id":2,"is_route":null,"name":"Lagos","name_en":null,"name_eu":null,"slug":null,"supercategory_id":1,"updated_at":"2013-02-11T10:57:13Z","icon_urls":{"small":"/icons/small/missing.png","med":"/icons/med/missing.png","big":"/icons/big/missing.png"}},{"created_at":"2013-02-11T10:57:13Z","description":null,"foursquare_icon":null,"foursquare_id":null,"group":"tosee","icon_content_type":null,"icon_file_name":null,"icon_file_size":null,"icon_update_at":null,"id":3,"is_route":null,"name":"Cuevas","name_en":null,"name_eu":null,"slug":null,"supercategory_id":1,"updated_at":"2013-02-11T10:57:13Z","icon_urls":{"small":"/icons/small/missing.png","med":"/icons/med/missing.png","big":"/icons/big/missing.png"}},{"created_at":"2013-02-11T10:57:13Z","description":null,"foursquare_icon":null,"foursquare_id":null,"group":"tosee","icon_content_type":null,"icon_file_name":null,"icon_file_size":null,"icon_update_at":null,"id":4,"is_route":null,"name":"Reservas Naturales","name_en":null,"name_eu":null,"slug":null,"supercategory_id":1,"updated_at":"2013-02-11T10:57:13Z","icon_urls":{"small":"/icons/small/missing.png","med":"/icons/med/missing.png","big":"/icons/big/missing.png"}},{"created_at":"2013-02-11T10:57:13Z","description":null,"foursquare_icon":null,"foursquare_id":null,"group":"tosee","icon_content_type":null,"icon_file_name":null,"icon_file_size":null,"icon_update_at":null,"id":5,"is_route":null,"name":"Bosques","name_en":null,"name_eu":null,"slug":null,"supercategory_id":1,"updated_at":"2013-02-11T10:57:13Z","icon_urls":{"small":"/icons/small/missing.png","med":"/icons/med/missing.png","big":"/icons/big/missing.png"}},{"created_at":"2013-02-11T10:57:13Z","description":null,"foursquare_icon":null,"foursquare_id":null,"group":"tosee","icon_content_type":null,"icon_file_name":null,"icon_file_size":null,"icon_update_at":null,"id":6,"is_route":null,"name":"Islas","name_en":null,"name_eu":null,"slug":null,"supercategory_id":1,"updated_at":"2013-02-11T10:57:13Z","icon_urls":{"small":"/icons/small/missing.png","med":"/icons/med/missing.png","big":"/icons/big/missing.png"}},{"created_at":"2013-02-11T10:57:13Z","description":null,"foursquare_icon":null,"foursquare_id":null,"group":"tosee","icon_content_type":null,"icon_file_name":null,"icon_file_size":null,"icon_update_at":null,"id":7,"is_route":null,"name":"R\u00edos","name_en":null,"name_eu":null,"slug":null,"supercategory_id":1,"updated_at":"2013-02-11T10:57:13Z","icon_urls":{"small":"/icons/small/missing.png","med":"/icons/med/missing.png","big":"/icons/big/missing.png"}},{"created_at":"2013-02-11T10:57:13Z","description":null,"foursquare_icon":null,"foursquare_id":null,"group":"tosee","icon_content_type":null,"icon_file_name":null,"icon_file_size":null,"icon_update_at":null,"id":8,"is_route":null,"name":"Miradores","name_en":null,"name_eu":null,"slug":null,"supercategory_id":1,"updated_at":"2013-02-11T10:57:13Z","icon_urls":{"small":"/icons/small/missing.png","med":"/icons/med/missing.png","big":"/icons/big/missing.png"}},{"created_at":"2013-02-11T10:57:13Z","description":null,"foursquare_icon":null,"foursquare_id":null,"group":"tosee","icon_content_type":null,"icon_file_name":null,"icon_file_size":null,"icon_update_at":null,"id":9,"is_route":null,"name":"Playas","name_en":null,"name_eu":null,"slug":null,"supercategory_id":1,"updated_at":"2013-02-11T10:57:13Z","icon_urls":{"small":"/icons/small/missing.png","med":"/icons/med/missing.png","big":"/icons/big/missing.png"}},{"created_at":"2013-02-11T10:57:13Z","description":null,"foursquare_icon":null,"foursquare_id":null,"group":"tosee","icon_content_type":null,"icon_file_name":null,"icon_file_size":null,"icon_update_at":null,"id":10,"is_route":null,"name":"Jardines","name_en":null,"name_eu":null,"slug":null,"supercategory_id":1,"updated_at":"2013-02-11T10:57:13Z","icon_urls":{"small":"/icons/small/missing.png","med":"/icons/med/missing.png","big":"/icons/big/missing.png"}},{"created_at":"2013-02-11T10:57:12Z","description":null,"foursquare_icon":null,"foursquare_id":null,"group":"tosee","icon_content_type":null,"icon_file_name":null,"icon_file_size":null,"icon_update_at":null,"id":11,"is_route":null,"name":"Museos","name_en":null,"name_eu":null,"slug":null,"supercategory_id":2,"updated_at":"2013-02-11T10:57:12Z","icon_urls":{"small":"/icons/small/missing.png","med":"/icons/med/missing.png","big":"/icons/big/missing.png"}},{"created_at":"2013-02-11T10:57:12Z","description":null,"foursquare_icon":null,"foursquare_id":null,"group":"tosee","icon_content_type":null,"icon_file_name":null,"icon_file_size":null,"icon_update_at":null,"id":12,"is_route":null,"name":"Castillos","name_en":null,"name_eu":null,"slug":null,"supercategory_id":2,"updated_at":"2013-02-11T10:57:12Z","icon_urls":{"small":"/icons/small/missing.png","med":"/icons/med/missing.png","big":"/icons/big/missing.png"}},{"created_at":"2013-02-11T10:57:12Z","description":null,"foursquare_icon":null,"foursquare_id":null,"group":"tosee","icon_content_type":null,"icon_file_name":null,"icon_file_size":null,"icon_update_at":null,"id":13,"is_route":null,"name":"Catedrales","name_en":null,"name_eu":null,"slug":null,"supercategory_id":2,"updated_at":"2013-02-11T10:57:12Z","icon_urls":{"small":"/icons/small/missing.png","med":"/icons/med/missing.png","big":"/icons/big/missing.png"}},{"created_at":"2013-02-11T10:57:12Z","description":null,"foursquare_icon":null,"foursquare_id":null,"group":"tosee","icon_content_type":null,"icon_file_name":null,"icon_file_size":null,"icon_update_at":null,"id":14,"is_route":null,"name":"Iglesias","name_en":null,"name_eu":null,"slug":null,"supercategory_id":2,"updated_at":"2013-02-11T10:57:12Z","icon_urls":{"small":"/icons/small/missing.png","med":"/icons/med/missing.png","big":"/icons/big/missing.png"}},{"created_at":"2013-02-11T10:57:12Z","description":null,"foursquare_icon":null,"foursquare_id":null,"group":"tosee","icon_content_type":null,"icon_file_name":null,"icon_file_size":null,"icon_update_at":null,"id":15,"is_route":null,"name":"Monumentos Hist\u00f3ricos","name_en":null,"name_eu":null,"slug":null,"supercategory_id":2,"updated_at":"2013-02-11T10:57:12Z","icon_urls":{"small":"/icons/small/missing.png","med":"/icons/med/missing.png","big":"/icons/big/missing.png"}},{"created_at":"2013-02-11T10:57:12Z","description":null,"foursquare_icon":null,"foursquare_id":null,"group":"tosee","icon_content_type":null,"icon_file_name":null,"icon_file_size":null,"icon_update_at":null,"id":16,"is_route":null,"name":"Estatuas","name_en":null,"name_eu":null,"slug":null,"supercategory_id":2,"updated_at":"2013-02-11T10:57:12Z","icon_urls":{"small":"/icons/small/missing.png","med":"/icons/med/missing.png","big":"/icons/big/missing.png"}},{"created_at":"2013-02-11T10:57:12Z","description":null,"foursquare_icon":null,"foursquare_id":null,"group":"sleep_paradors","icon_content_type":null,"icon_file_name":null,"icon_file_size":null,"icon_update_at":null,"id":17,"is_route":null,"name":"Paradores","name_en":null,"name_eu":null,"slug":null,"supercategory_id":2,"updated_at":"2013-02-11T10:57:12Z","icon_urls":{"small":"/icons/small/missing.png","med":"/icons/med/missing.png","big":"/icons/big/missing.png"}},{"created_at":"2013-02-11T10:57:12Z","description":null,"foursquare_icon":null,"foursquare_id":null,"group":"tosee","icon_content_type":null,"icon_file_name":null,"icon_file_size":null,"icon_update_at":null,"id":18,"is_route":null,"name":"Ayuntamientos","name_en":null,"name_eu":null,"slug":null,"supercategory_id":2,"updated_at":"2013-02-11T10:57:12Z","icon_urls":{"small":"/icons/small/missing.png","med":"/icons/med/missing.png","big":"/icons/big/missing.png"}},{"created_at":"2013-02-11T10:57:12Z","description":null,"foursquare_icon":null,"foursquare_id":null,"group":"tosee","icon_content_type":null,"icon_file_name":null,"icon_file_size":null,"icon_update_at":null,"id":19,"is_route":null,"name":"Palacios","name_en":null,"name_eu":null,"slug":null,"supercategory_id":2,"updated_at":"2013-02-11T10:57:12Z","icon_urls":{"small":"/icons/small/missing.png","med":"/icons/med/missing.png","big":"/icons/big/missing.png"}},{"created_at":"2013-02-11T10:57:13Z","description":null,"foursquare_icon":null,"foursquare_id":null,"group":"do","icon_content_type":null,"icon_file_name":null,"icon_file_size":null,"icon_update_at":null,"id":20,"is_route":null,"name":"Parques Acu\u00e1ticos","name_en":null,"name_eu":null,"slug":null,"supercategory_id":3,"updated_at":"2013-02-11T10:57:13Z","icon_urls":{"small":"/icons/small/missing.png","med":"/icons/med/missing.png","big":"/icons/big/missing.png"}},{"created_at":"2013-02-11T10:57:13Z","description":null,"foursquare_icon":null,"foursquare_id":null,"group":"do","icon_content_type":null,"icon_file_name":null,"icon_file_size":null,"icon_update_at":null,"id":21,"is_route":null,"name":"Zoos","name_en":null,"name_eu":null,"slug":null,"supercategory_id":3,"updated_at":"2013-02-11T10:57:13Z","icon_urls":{"small":"/icons/small/missing.png","med":"/icons/med/missing.png","big":"/icons/big/missing.png"}},{"created_at":"2013-02-11T10:57:13Z","description":null,"foursquare_icon":null,"foursquare_id":null,"group":"do","icon_content_type":null,"icon_file_name":null,"icon_file_size":null,"icon_update_at":null,"id":22,"is_route":null,"name":"Safari","name_en":null,"name_eu":null,"slug":null,"supercategory_id":3,"updated_at":"2013-02-11T10:57:13Z","icon_urls":{"small":"/icons/small/missing.png","med":"/icons/med/missing.png","big":"/icons/big/missing.png"}},{"created_at":"2013-02-11T10:57:13Z","description":null,"foursquare_icon":null,"foursquare_id":null,"group":"do","icon_content_type":null,"icon_file_name":null,"icon_file_size":null,"icon_update_at":null,"id":23,"is_route":null,"name":"Parques Tem\u00e1ticos","name_en":null,"name_eu":null,"slug":null,"supercategory_id":3,"updated_at":"2013-02-11T10:57:13Z","icon_urls":{"small":"/icons/small/missing.png","med":"/icons/med/missing.png","big":"/icons/big/missing.png"}},{"created_at":"2013-02-11T10:57:13Z","description":null,"foursquare_icon":null,"foursquare_id":null,"group":"do","icon_content_type":null,"icon_file_name":null,"icon_file_size":null,"icon_update_at":null,"id":24,"is_route":null,"name":"Parques de Atracciones","name_en":null,"name_eu":null,"slug":null,"supercategory_id":3,"updated_at":"2013-02-11T10:57:13Z","icon_urls":{"small":"/icons/small/missing.png","med":"/icons/med/missing.png","big":"/icons/big/missing.png"}},{"created_at":"2013-02-11T10:57:13Z","description":null,"foursquare_icon":null,"foursquare_id":null,"group":"do","icon_content_type":null,"icon_file_name":null,"icon_file_size":null,"icon_update_at":null,"id":25,"is_route":null,"name":"Centros Comerciales","name_en":null,"name_eu":null,"slug":null,"supercategory_id":3,"updated_at":"2013-02-11T10:57:13Z","icon_urls":{"small":"/icons/small/missing.png","med":"/icons/med/missing.png","big":"/icons/big/missing.png"}},{"created_at":"2013-02-11T10:57:13Z","description":null,"foursquare_icon":null,"foursquare_id":null,"group":"do","icon_content_type":null,"icon_file_name":null,"icon_file_size":null,"icon_update_at":null,"id":26,"is_route":null,"name":"Zonas de Compras","name_en":null,"name_eu":null,"slug":null,"supercategory_id":3,"updated_at":"2013-02-11T10:57:13Z","icon_urls":{"small":"/icons/small/missing.png","med":"/icons/med/missing.png","big":"/icons/big/missing.png"}},{"created_at":"2013-02-11T10:57:13Z","description":null,"foursquare_icon":null,"foursquare_id":null,"group":"do","icon_content_type":null,"icon_file_name":null,"icon_file_size":null,"icon_update_at":null,"id":27,"is_route":null,"name":"Tiendas","name_en":null,"name_eu":null,"slug":null,"supercategory_id":3,"updated_at":"2013-02-11T10:57:13Z","icon_urls":{"small":"/icons/small/missing.png","med":"/icons/med/missing.png","big":"/icons/big/missing.png"}},{"created_at":"2013-02-11T10:57:13Z","description":null,"foursquare_icon":null,"foursquare_id":null,"group":"do","icon_content_type":null,"icon_file_name":null,"icon_file_size":null,"icon_update_at":null,"id":28,"is_route":null,"name":"Cines","name_en":null,"name_eu":null,"slug":null,"supercategory_id":3,"updated_at":"2013-02-11T10:57:13Z","icon_urls":{"small":"/icons/small/missing.png","med":"/icons/med/missing.png","big":"/icons/big/missing.png"}},{"created_at":"2013-02-11T10:57:13Z","description":null,"foursquare_icon":null,"foursquare_id":null,"group":"eat","icon_content_type":null,"icon_file_name":null,"icon_file_size":null,"icon_update_at":null,"id":29,"is_route":null,"name":"Restaurantes","name_en":null,"name_eu":null,"slug":null,"supercategory_id":3,"updated_at":"2013-02-11T10:57:13Z","icon_urls":{"small":"/icons/small/missing.png","med":"/icons/med/missing.png","big":"/icons/big/missing.png"}},{"created_at":"2013-02-11T10:57:13Z","description":null,"foursquare_icon":null,"foursquare_id":null,"group":"do","icon_content_type":null,"icon_file_name":null,"icon_file_size":null,"icon_update_at":null,"id":30,"is_route":null,"name":"Centros de Internet","name_en":null,"name_eu":null,"slug":null,"supercategory_id":3,"updated_at":"2013-02-11T10:57:13Z","icon_urls":{"small":"/icons/small/missing.png","med":"/icons/med/missing.png","big":"/icons/big/missing.png"}},{"created_at":"2013-02-11T10:57:13Z","description":null,"foursquare_icon":null,"foursquare_id":null,"group":"do","icon_content_type":null,"icon_file_name":null,"icon_file_size":null,"icon_update_at":null,"id":31,"is_route":null,"name":"Balnearios","name_en":null,"name_eu":null,"slug":null,"supercategory_id":3,"updated_at":"2013-02-11T10:57:13Z","icon_urls":{"small":"/icons/small/missing.png","med":"/icons/med/missing.png","big":"/icons/big/missing.png"}},{"created_at":"2013-02-11T10:57:13Z","description":null,"foursquare_icon":null,"foursquare_id":null,"group":"do","icon_content_type":null,"icon_file_name":null,"icon_file_size":null,"icon_update_at":null,"id":32,"is_route":null,"name":"Centros de Belleza","name_en":null,"name_eu":null,"slug":null,"supercategory_id":3,"updated_at":"2013-02-11T10:57:13Z","icon_urls":{"small":"/icons/small/missing.png","med":"/icons/med/missing.png","big":"/icons/big/missing.png"}},{"created_at":"2013-02-11T10:57:13Z","description":null,"foursquare_icon":null,"foursquare_id":null,"group":"do","icon_content_type":null,"icon_file_name":null,"icon_file_size":null,"icon_update_at":null,"id":33,"is_route":null,"name":"Spa","name_en":null,"name_eu":null,"slug":null,"supercategory_id":3,"updated_at":"2013-02-11T10:57:13Z","icon_urls":{"small":"/icons/small/missing.png","med":"/icons/med/missing.png","big":"/icons/big/missing.png"}},{"created_at":"2013-02-11T10:57:13Z","description":null,"foursquare_icon":null,"foursquare_id":null,"group":"do","icon_content_type":null,"icon_file_name":null,"icon_file_size":null,"icon_update_at":null,"id":34,"is_route":null,"name":"Bares de Tapas","name_en":null,"name_eu":null,"slug":null,"supercategory_id":3,"updated_at":"2013-02-11T10:57:13Z","icon_urls":{"small":"/icons/small/missing.png","med":"/icons/med/missing.png","big":"/icons/big/missing.png"}},{"created_at":"2013-02-11T10:57:13Z","description":null,"foursquare_icon":null,"foursquare_id":null,"group":"eat","icon_content_type":null,"icon_file_name":null,"icon_file_size":null,"icon_update_at":null,"id":36,"is_route":null,"name":"Inter\u00e9s Gastron\u00f3mico","name_en":null,"name_eu":null,"slug":null,"supercategory_id":3,"updated_at":"2013-02-11T10:57:13Z","icon_urls":{"small":"/icons/small/missing.png","med":"/icons/med/missing.png","big":"/icons/big/missing.png"}},{"created_at":"2013-02-11T10:57:13Z","description":null,"foursquare_icon":null,"foursquare_id":null,"group":"do","icon_content_type":null,"icon_file_name":null,"icon_file_size":null,"icon_update_at":null,"id":37,"is_route":null,"name":"Casinos","name_en":null,"name_eu":null,"slug":null,"supercategory_id":3,"updated_at":"2013-02-11T10:57:13Z","icon_urls":{"small":"/icons/small/missing.png","med":"/icons/med/missing.png","big":"/icons/big/missing.png"}},{"created_at":"2013-02-11T10:57:13Z","description":null,"foursquare_icon":null,"foursquare_id":null,"group":"do","icon_content_type":null,"icon_file_name":null,"icon_file_size":null,"icon_update_at":null,"id":38,"is_route":null,"name":"Boleras","name_en":null,"name_eu":null,"slug":null,"supercategory_id":3,"updated_at":"2013-02-11T10:57:13Z","icon_urls":{"small":"/icons/small/missing.png","med":"/icons/med/missing.png","big":"/icons/big/missing.png"}},{"created_at":"2013-02-11T10:57:13Z","description":null,"foursquare_icon":null,"foursquare_id":null,"group":"do","icon_content_type":null,"icon_file_name":null,"icon_file_size":null,"icon_update_at":null,"id":39,"is_route":null,"name":"Discotecas","name_en":null,"name_eu":null,"slug":null,"supercategory_id":3,"updated_at":"2013-02-11T10:57:13Z","icon_urls":{"small":"/icons/small/missing.png","med":"/icons/med/missing.png","big":"/icons/big/missing.png"}},{"created_at":"2013-02-11T10:57:13Z","description":null,"foursquare_icon":null,"foursquare_id":null,"group":"do","icon_content_type":null,"icon_file_name":null,"icon_file_size":null,"icon_update_at":null,"id":40,"is_route":null,"name":"Bares de Copas","name_en":null,"name_eu":null,"slug":null,"supercategory_id":3,"updated_at":"2013-02-11T10:57:13Z","icon_urls":{"small":"/icons/small/missing.png","med":"/icons/med/missing.png","big":"/icons/big/missing.png"}},{"created_at":"2013-02-11T10:57:13Z","description":null,"foursquare_icon":null,"foursquare_id":null,"group":"do","icon_content_type":null,"icon_file_name":null,"icon_file_size":null,"icon_update_at":null,"id":41,"is_route":null,"name":"Zonas de Copas","name_en":null,"name_eu":null,"slug":null,"supercategory_id":3,"updated_at":"2013-02-11T10:57:13Z","icon_urls":{"small":"/icons/small/missing.png","med":"/icons/med/missing.png","big":"/icons/big/missing.png"}},{"created_at":"2013-02-11T10:57:13Z","description":null,"foursquare_icon":null,"foursquare_id":null,"group":"do","icon_content_type":null,"icon_file_name":null,"icon_file_size":null,"icon_update_at":null,"id":42,"is_route":null,"name":"Salas de Conciertos","name_en":null,"name_eu":null,"slug":null,"supercategory_id":3,"updated_at":"2013-02-11T10:57:13Z","icon_urls":{"small":"/icons/small/missing.png","med":"/icons/med/missing.png","big":"/icons/big/missing.png"}},{"created_at":"2013-02-11T10:57:13Z","description":null,"foursquare_icon":null,"foursquare_id":null,"group":"eat","icon_content_type":null,"icon_file_name":null,"icon_file_size":null,"icon_update_at":null,"id":43,"is_route":null,"name":"Cafeter\u00edas","name_en":null,"name_eu":null,"slug":null,"supercategory_id":3,"updated_at":"2013-02-11T10:57:13Z","icon_urls":{"small":"/icons/small/missing.png","med":"/icons/med/missing.png","big":"/icons/big/missing.png"}},{"created_at":"2013-02-11T10:57:13Z","description":null,"foursquare_icon":null,"foursquare_id":null,"group":"do","icon_content_type":null,"icon_file_name":null,"icon_file_size":null,"icon_update_at":null,"id":44,"is_route":null,"name":"Estadios","name_en":null,"name_eu":null,"slug":null,"supercategory_id":3,"updated_at":"2013-02-11T10:57:13Z","icon_urls":{"small":"/icons/small/missing.png","med":"/icons/med/missing.png","big":"/icons/big/missing.png"}},{"created_at":"2013-02-11T10:57:13Z","description":null,"foursquare_icon":null,"foursquare_id":null,"group":"do","icon_content_type":null,"icon_file_name":null,"icon_file_size":null,"icon_update_at":null,"id":45,"is_route":null,"name":"Circuitos de Carreras","name_en":null,"name_eu":null,"slug":null,"supercategory_id":3,"updated_at":"2013-02-11T10:57:13Z","icon_urls":{"small":"/icons/small/missing.png","med":"/icons/med/missing.png","big":"/icons/big/missing.png"}},{"created_at":"2013-02-11T10:57:12Z","description":null,"foursquare_icon":null,"foursquare_id":null,"group":"do","icon_content_type":null,"icon_file_name":null,"icon_file_size":null,"icon_update_at":null,"id":47,"is_route":null,"name":"Escalada","name_en":null,"name_eu":null,"slug":null,"supercategory_id":4,"updated_at":"2013-02-11T10:57:12Z","icon_urls":{"small":"/icons/small/missing.png","med":"/icons/med/missing.png","big":"/icons/big/missing.png"}},{"created_at":"2013-02-11T10:57:12Z","description":null,"foursquare_icon":null,"foursquare_id":null,"group":"do","icon_content_type":null,"icon_file_name":null,"icon_file_size":null,"icon_update_at":null,"id":48,"is_route":null,"name":"Rafting","name_en":null,"name_eu":null,"slug":null,"supercategory_id":4,"updated_at":"2013-02-11T10:57:12Z","icon_urls":{"small":"/icons/small/missing.png","med":"/icons/med/missing.png","big":"/icons/big/missing.png"}},{"created_at":"2013-02-11T10:57:12Z","description":null,"foursquare_icon":null,"foursquare_id":null,"group":"do","icon_content_type":null,"icon_file_name":null,"icon_file_size":null,"icon_update_at":null,"id":49,"is_route":null,"name":"Esqu\u00ed","name_en":null,"name_eu":null,"slug":null,"supercategory_id":4,"updated_at":"2013-02-11T10:57:12Z","icon_urls":{"small":"/icons/small/missing.png","med":"/icons/med/missing.png","big":"/icons/big/missing.png"}},{"created_at":"2013-02-11T10:57:12Z","description":null,"foursquare_icon":null,"foursquare_id":null,"group":"do","icon_content_type":null,"icon_file_name":null,"icon_file_size":null,"icon_update_at":null,"id":50,"is_route":null,"name":"Campos de Golf","name_en":null,"name_eu":null,"slug":null,"supercategory_id":4,"updated_at":"2013-02-11T10:57:12Z","icon_urls":{"small":"/icons/small/missing.png","med":"/icons/med/missing.png","big":"/icons/big/missing.png"}},{"created_at":"2013-02-11T10:57:12Z","description":null,"foursquare_icon":null,"foursquare_id":null,"group":"do","icon_content_type":null,"icon_file_name":null,"icon_file_size":null,"icon_update_at":null,"id":51,"is_route":null,"name":"Campos de F\u00fatbol","name_en":null,"name_eu":null,"slug":null,"supercategory_id":4,"updated_at":"2013-02-11T10:57:12Z","icon_urls":{"small":"/icons/small/missing.png","med":"/icons/med/missing.png","big":"/icons/big/missing.png"}},{"created_at":"2013-02-11T10:57:12Z","description":null,"foursquare_icon":null,"foursquare_id":null,"group":"do","icon_content_type":null,"icon_file_name":null,"icon_file_size":null,"icon_update_at":null,"id":52,"is_route":null,"name":"Carril bici","name_en":null,"name_eu":null,"slug":null,"supercategory_id":4,"updated_at":"2013-02-11T10:57:12Z","icon_urls":{"small":"/icons/small/missing.png","med":"/icons/med/missing.png","big":"/icons/big/missing.png"}},{"created_at":"2013-02-11T10:57:12Z","description":null,"foursquare_icon":null,"foursquare_id":null,"group":"do","icon_content_type":null,"icon_file_name":null,"icon_file_size":null,"icon_update_at":null,"id":53,"is_route":null,"name":"Senderismo","name_en":null,"name_eu":null,"slug":null,"supercategory_id":4,"updated_at":"2013-02-11T10:57:12Z","icon_urls":{"small":"/icons/small/missing.png","med":"/icons/med/missing.png","big":"/icons/big/missing.png"}},{"created_at":"2013-02-11T10:57:12Z","description":null,"foursquare_icon":null,"foursquare_id":null,"group":"do","icon_content_type":null,"icon_file_name":null,"icon_file_size":null,"icon_update_at":null,"id":54,"is_route":null,"name":"Gimnasios","name_en":null,"name_eu":null,"slug":null,"supercategory_id":4,"updated_at":"2013-02-11T10:57:12Z","icon_urls":{"small":"/icons/small/missing.png","med":"/icons/med/missing.png","big":"/icons/big/missing.png"}},{"created_at":"2013-02-11T10:57:12Z","description":null,"foursquare_icon":null,"foursquare_id":null,"group":"do","icon_content_type":null,"icon_file_name":null,"icon_file_size":null,"icon_update_at":null,"id":55,"is_route":null,"name":"Paintball","name_en":null,"name_eu":null,"slug":null,"supercategory_id":4,"updated_at":"2013-02-11T10:57:12Z","icon_urls":{"small":"/icons/small/missing.png","med":"/icons/med/missing.png","big":"/icons/big/missing.png"}},{"created_at":"2013-02-11T10:57:12Z","description":null,"foursquare_icon":null,"foursquare_id":null,"group":"do","icon_content_type":null,"icon_file_name":null,"icon_file_size":null,"icon_update_at":null,"id":56,"is_route":null,"name":"Pistas de Tenis","name_en":null,"name_eu":null,"slug":null,"supercategory_id":4,"updated_at":"2013-02-11T10:57:12Z","icon_urls":{"small":"/icons/small/missing.png","med":"/icons/med/missing.png","big":"/icons/big/missing.png"}},{"created_at":"2013-02-11T10:57:12Z","description":null,"foursquare_icon":null,"foursquare_id":null,"group":"do","icon_content_type":null,"icon_file_name":null,"icon_file_size":null,"icon_update_at":null,"id":57,"is_route":null,"name":"Pistas de Padel","name_en":null,"name_eu":null,"slug":null,"supercategory_id":4,"updated_at":"2013-02-11T10:57:12Z","icon_urls":{"small":"/icons/small/missing.png","med":"/icons/med/missing.png","big":"/icons/big/missing.png"}},{"created_at":"2013-02-11T10:57:12Z","description":null,"foursquare_icon":null,"foursquare_id":null,"group":"do","icon_content_type":null,"icon_file_name":null,"icon_file_size":null,"icon_update_at":null,"id":58,"is_route":null,"name":"Polideportivos","name_en":null,"name_eu":null,"slug":null,"supercategory_id":4,"updated_at":"2013-02-11T10:57:12Z","icon_urls":{"small":"/icons/small/missing.png","med":"/icons/med/missing.png","big":"/icons/big/missing.png"}},{"created_at":"2013-02-11T10:57:12Z","description":null,"foursquare_icon":null,"foursquare_id":null,"group":"do","icon_content_type":null,"icon_file_name":null,"icon_file_size":null,"icon_update_at":null,"id":59,"is_route":null,"name":"Kite Surf","name_en":null,"name_eu":null,"slug":null,"supercategory_id":4,"updated_at":"2013-02-11T10:57:12Z","icon_urls":{"small":"/icons/small/missing.png","med":"/icons/med/missing.png","big":"/icons/big/missing.png"}},{"created_at":"2013-02-11T10:57:12Z","description":null,"foursquare_icon":null,"foursquare_id":null,"group":"do","icon_content_type":null,"icon_file_name":null,"icon_file_size":null,"icon_update_at":null,"id":60,"is_route":null,"name":"Skate","name_en":null,"name_eu":null,"slug":null,"supercategory_id":4,"updated_at":"2013-02-11T10:57:12Z","icon_urls":{"small":"/icons/small/missing.png","med":"/icons/med/missing.png","big":"/icons/big/missing.png"}},{"created_at":"2013-02-11T10:57:12Z","description":null,"foursquare_icon":null,"foursquare_id":null,"group":"do","icon_content_type":null,"icon_file_name":null,"icon_file_size":null,"icon_update_at":null,"id":61,"is_route":null,"name":"Surf","name_en":null,"name_eu":null,"slug":null,"supercategory_id":4,"updated_at":"2013-02-11T10:57:12Z","icon_urls":{"small":"/icons/small/missing.png","med":"/icons/med/missing.png","big":"/icons/big/missing.png"}},{"created_at":"2013-02-11T10:57:12Z","description":null,"foursquare_icon":null,"foursquare_id":null,"group":"do","icon_content_type":null,"icon_file_name":null,"icon_file_size":null,"icon_update_at":null,"id":62,"is_route":null,"name":"Paracaidismo","name_en":null,"name_eu":null,"slug":null,"supercategory_id":4,"updated_at":"2013-02-11T10:57:12Z","icon_urls":{"small":"/icons/small/missing.png","med":"/icons/med/missing.png","big":"/icons/big/missing.png"}},{"created_at":"2013-02-11T10:57:12Z","description":null,"foursquare_icon":null,"foursquare_id":null,"group":"do","icon_content_type":null,"icon_file_name":null,"icon_file_size":null,"icon_update_at":null,"id":64,"is_route":null,"name":"Competiciones Deportivas","name_en":null,"name_eu":null,"slug":null,"supercategory_id":5,"updated_at":"2013-02-11T10:57:12Z","icon_urls":{"small":"/icons/small/missing.png","med":"/icons/med/missing.png","big":"/icons/big/missing.png"}},{"created_at":"2013-02-11T10:57:12Z","description":null,"foursquare_icon":null,"foursquare_id":null,"group":"do","icon_content_type":null,"icon_file_name":null,"icon_file_size":null,"icon_update_at":null,"id":65,"is_route":null,"name":"Fiestas","name_en":null,"name_eu":null,"slug":null,"supercategory_id":5,"updated_at":"2013-02-11T10:57:12Z","icon_urls":{"small":"/icons/small/missing.png","med":"/icons/med/missing.png","big":"/icons/big/missing.png"}},{"created_at":"2013-02-11T10:57:12Z","description":null,"foursquare_icon":null,"foursquare_id":null,"group":"do","icon_content_type":null,"icon_file_name":null,"icon_file_size":null,"icon_update_at":null,"id":66,"is_route":null,"name":"Conciertos","name_en":null,"name_eu":null,"slug":null,"supercategory_id":5,"updated_at":"2013-02-11T10:57:12Z","icon_urls":{"small":"/icons/small/missing.png","med":"/icons/med/missing.png","big":"/icons/big/missing.png"}},{"created_at":"2013-02-11T10:57:12Z","description":null,"foursquare_icon":null,"foursquare_id":null,"group":"do","icon_content_type":null,"icon_file_name":null,"icon_file_size":null,"icon_update_at":null,"id":67,"is_route":null,"name":"Musicales","name_en":null,"name_eu":null,"slug":null,"supercategory_id":5,"updated_at":"2013-02-11T10:57:12Z","icon_urls":{"small":"/icons/small/missing.png","med":"/icons/med/missing.png","big":"/icons/big/missing.png"}},{"created_at":"2013-02-11T10:57:12Z","description":null,"foursquare_icon":null,"foursquare_id":null,"group":"sleep_hotels","icon_content_type":null,"icon_file_name":null,"icon_file_size":null,"icon_update_at":null,"id":68,"is_route":null,"name":"Hoteles","name_en":null,"name_eu":null,"slug":null,"supercategory_id":6,"updated_at":"2013-02-11T10:57:12Z","icon_urls":{"small":"/icons/small/missing.png","med":"/icons/med/missing.png","big":"/icons/big/missing.png"}},{"created_at":"2013-02-11T10:57:12Z","description":null,"foursquare_icon":null,"foursquare_id":null,"group":"sleep_rural","icon_content_type":null,"icon_file_name":null,"icon_file_size":null,"icon_update_at":null,"id":69,"is_route":null,"name":"Casas Rurales","name_en":null,"name_eu":null,"slug":null,"supercategory_id":6,"updated_at":"2013-02-11T10:57:12Z","icon_urls":{"small":"/icons/small/missing.png","med":"/icons/med/missing.png","big":"/icons/big/missing.png"}},{"created_at":"2013-02-11T10:57:12Z","description":null,"foursquare_icon":null,"foursquare_id":null,"group":"sleep_hostals","icon_content_type":null,"icon_file_name":null,"icon_file_size":null,"icon_update_at":null,"id":70,"is_route":null,"name":"Hostales","name_en":null,"name_eu":null,"slug":null,"supercategory_id":6,"updated_at":"2013-02-11T10:57:12Z","icon_urls":{"small":"/icons/small/missing.png","med":"/icons/med/missing.png","big":"/icons/big/missing.png"}},{"created_at":"2013-02-11T10:57:12Z","description":null,"foursquare_icon":null,"foursquare_id":null,"group":"sleep_bungalows","icon_content_type":null,"icon_file_name":null,"icon_file_size":null,"icon_update_at":null,"id":71,"is_route":null,"name":"Bungalows","name_en":null,"name_eu":null,"slug":null,"supercategory_id":6,"updated_at":"2013-02-11T10:57:12Z","icon_urls":{"small":"/icons/small/missing.png","med":"/icons/med/missing.png","big":"/icons/big/missing.png"}},{"created_at":"2013-02-11T10:57:12Z","description":null,"foursquare_icon":null,"foursquare_id":null,"group":"sleep_apartments","icon_content_type":null,"icon_file_name":null,"icon_file_size":null,"icon_update_at":null,"id":72,"is_route":null,"name":"Apartamentos","name_en":null,"name_eu":null,"slug":null,"supercategory_id":6,"updated_at":"2013-02-11T10:57:12Z","icon_urls":{"small":"/icons/small/missing.png","med":"/icons/med/missing.png","big":"/icons/big/missing.png"}},{"created_at":"2013-02-11T10:57:12Z","description":null,"foursquare_icon":null,"foursquare_id":null,"group":"sleep_aparthotels","icon_content_type":null,"icon_file_name":null,"icon_file_size":null,"icon_update_at":null,"id":73,"is_route":null,"name":"Aparthoteles","name_en":null,"name_eu":null,"slug":null,"supercategory_id":6,"updated_at":"2013-02-11T10:57:12Z","icon_urls":{"small":"/icons/small/missing.png","med":"/icons/med/missing.png","big":"/icons/big/missing.png"}},{"created_at":"2013-02-11T10:57:12Z","description":null,"foursquare_icon":null,"foursquare_id":null,"group":"sleep_campings","icon_content_type":null,"icon_file_name":null,"icon_file_size":null,"icon_update_at":null,"id":74,"is_route":null,"name":"Campings","name_en":null,"name_eu":null,"slug":null,"supercategory_id":6,"updated_at":"2013-02-11T10:57:12Z","icon_urls":{"small":"/icons/small/missing.png","med":"/icons/med/missing.png","big":"/icons/big/missing.png"}},{"created_at":"2013-02-11T10:57:13Z","description":null,"foursquare_icon":null,"foursquare_id":null,"group":"tosee","icon_content_type":null,"icon_file_name":null,"icon_file_size":null,"icon_update_at":null,"id":75,"is_route":null,"name":"Aeropuertos","name_en":null,"name_eu":null,"slug":null,"supercategory_id":7,"updated_at":"2013-02-11T10:57:13Z","icon_urls":{"small":"/icons/small/missing.png","med":"/icons/med/missing.png","big":"/icons/big/missing.png"}},{"created_at":"2013-02-11T10:57:13Z","description":null,"foursquare_icon":null,"foursquare_id":null,"group":"tosee","icon_content_type":null,"icon_file_name":null,"icon_file_size":null,"icon_update_at":null,"id":76,"is_route":null,"name":"Puertos","name_en":null,"name_eu":null,"slug":null,"supercategory_id":7,"updated_at":"2013-02-11T10:57:13Z","icon_urls":{"small":"/icons/small/missing.png","med":"/icons/med/missing.png","big":"/icons/big/missing.png"}},{"created_at":"2013-02-11T10:57:13Z","description":null,"foursquare_icon":null,"foursquare_id":null,"group":"tosee","icon_content_type":null,"icon_file_name":null,"icon_file_size":null,"icon_update_at":null,"id":77,"is_route":null,"name":"Estaciones de Tren","name_en":null,"name_eu":null,"slug":null,"supercategory_id":7,"updated_at":"2013-02-11T10:57:13Z","icon_urls":{"small":"/icons/small/missing.png","med":"/icons/med/missing.png","big":"/icons/big/missing.png"}},{"created_at":"2013-02-11T10:57:13Z","description":null,"foursquare_icon":null,"foursquare_id":null,"group":"tosee","icon_content_type":null,"icon_file_name":null,"icon_file_size":null,"icon_update_at":null,"id":78,"is_route":null,"name":"Estaciones de Autob\u00fas","name_en":null,"name_eu":null,"slug":null,"supercategory_id":7,"updated_at":"2013-02-11T10:57:13Z","icon_urls":{"small":"/icons/small/missing.png","med":"/icons/med/missing.png","big":"/icons/big/missing.png"}},{"created_at":"2013-02-11T10:57:13Z","description":null,"foursquare_icon":null,"foursquare_id":null,"group":"tosee","icon_content_type":null,"icon_file_name":null,"icon_file_size":null,"icon_update_at":null,"id":79,"is_route":null,"name":"Pantanos","name_en":null,"name_eu":null,"slug":null,"supercategory_id":1,"updated_at":"2013-02-11T10:57:13Z","icon_urls":{"small":"/icons/small/missing.png","med":"/icons/med/missing.png","big":"/icons/big/missing.png"}},{"created_at":"2013-02-11T10:57:13Z","description":null,"foursquare_icon":null,"foursquare_id":null,"group":"tosee","icon_content_type":null,"icon_file_name":null,"icon_file_size":null,"icon_update_at":null,"id":80,"is_route":null,"name":"Acantilados","name_en":null,"name_eu":null,"slug":null,"supercategory_id":1,"updated_at":"2013-02-11T10:57:13Z","icon_urls":{"small":"/icons/small/missing.png","med":"/icons/med/missing.png","big":"/icons/big/missing.png"}},{"created_at":"2013-02-11T10:57:13Z","description":null,"foursquare_icon":null,"foursquare_id":null,"group":"tosee","icon_content_type":null,"icon_file_name":null,"icon_file_size":null,"icon_update_at":null,"id":81,"is_route":null,"name":"De inter\u00e9s tur\u00edstico","name_en":null,"name_eu":null,"slug":null,"supercategory_id":1,"updated_at":"2013-02-11T10:57:13Z","icon_urls":{"small":"/icons/small/missing.png","med":"/icons/med/missing.png","big":"/icons/big/missing.png"}},{"created_at":"2013-02-11T10:57:12Z","description":null,"foursquare_icon":null,"foursquare_id":null,"group":"tosee","icon_content_type":null,"icon_file_name":null,"icon_file_size":null,"icon_update_at":null,"id":82,"is_route":null,"name":"Exposiciones","name_en":null,"name_eu":null,"slug":null,"supercategory_id":2,"updated_at":"2013-02-11T10:57:12Z","icon_urls":{"small":"/icons/small/missing.png","med":"/icons/med/missing.png","big":"/icons/big/missing.png"}},{"created_at":"2013-02-11T10:57:12Z","description":null,"foursquare_icon":null,"foursquare_id":null,"group":"tosee","icon_content_type":null,"icon_file_name":null,"icon_file_size":null,"icon_update_at":null,"id":83,"is_route":null,"name":"De inter\u00e9s cultural","name_en":null,"name_eu":null,"slug":null,"supercategory_id":2,"updated_at":"2013-02-11T10:57:12Z","icon_urls":{"small":"/icons/small/missing.png","med":"/icons/med/missing.png","big":"/icons/big/missing.png"}},{"created_at":"2013-02-11T10:57:13Z","description":null,"foursquare_icon":null,"foursquare_id":null,"group":"eat","icon_content_type":null,"icon_file_name":null,"icon_file_size":null,"icon_update_at":null,"id":84,"is_route":null,"name":"Coffee Shops","name_en":null,"name_eu":null,"slug":null,"supercategory_id":3,"updated_at":"2013-02-11T10:57:13Z","icon_urls":{"small":"/icons/small/missing.png","med":"/icons/med/missing.png","big":"/icons/big/missing.png"}},{"created_at":"2013-02-11T10:57:13Z","description":null,"foursquare_icon":null,"foursquare_id":null,"group":"eat","icon_content_type":null,"icon_file_name":null,"icon_file_size":null,"icon_update_at":null,"id":85,"is_route":null,"name":"Teter\u00edas","name_en":null,"name_eu":null,"slug":null,"supercategory_id":3,"updated_at":"2013-02-11T10:57:13Z","icon_urls":{"small":"/icons/small/missing.png","med":"/icons/med/missing.png","big":"/icons/big/missing.png"}},{"created_at":"2013-02-11T10:57:13Z","description":null,"foursquare_icon":null,"foursquare_id":null,"group":"do","icon_content_type":null,"icon_file_name":null,"icon_file_size":null,"icon_update_at":null,"id":86,"is_route":null,"name":"Cabaret","name_en":null,"name_eu":null,"slug":null,"supercategory_id":3,"updated_at":"2013-02-11T10:57:13Z","icon_urls":{"small":"/icons/small/missing.png","med":"/icons/med/missing.png","big":"/icons/big/missing.png"}},{"created_at":"2013-02-11T10:57:12Z","description":null,"foursquare_icon":null,"foursquare_id":null,"group":"do","icon_content_type":null,"icon_file_name":null,"icon_file_size":null,"icon_update_at":null,"id":87,"is_route":null,"name":"De inter\u00e9s deportivo","name_en":null,"name_eu":null,"slug":null,"supercategory_id":4,"updated_at":"2013-02-11T10:57:12Z","icon_urls":{"small":"/icons/small/missing.png","med":"/icons/med/missing.png","big":"/icons/big/missing.png"}},{"created_at":"2013-02-11T10:57:12Z","description":null,"foursquare_icon":null,"foursquare_id":null,"group":"do","icon_content_type":null,"icon_file_name":null,"icon_file_size":null,"icon_update_at":null,"id":88,"is_route":null,"name":"Club deportivo ni\u00f1os","name_en":null,"name_eu":null,"slug":null,"supercategory_id":4,"updated_at":"2013-02-11T10:57:12Z","icon_urls":{"small":"/icons/small/missing.png","med":"/icons/med/missing.png","big":"/icons/big/missing.png"}},{"created_at":"2013-02-11T10:57:12Z","description":null,"foursquare_icon":null,"foursquare_id":null,"group":"do","icon_content_type":null,"icon_file_name":null,"icon_file_size":null,"icon_update_at":null,"id":89,"is_route":null,"name":"Jet Sky","name_en":null,"name_eu":null,"slug":null,"supercategory_id":4,"updated_at":"2013-02-11T10:57:12Z","icon_urls":{"small":"/icons/small/missing.png","med":"/icons/med/missing.png","big":"/icons/big/missing.png"}},{"created_at":"2013-02-11T10:57:12Z","description":null,"foursquare_icon":null,"foursquare_id":null,"group":"do","icon_content_type":null,"icon_file_name":null,"icon_file_size":null,"icon_update_at":null,"id":90,"is_route":null,"name":"Wakeboard","name_en":null,"name_eu":null,"slug":null,"supercategory_id":4,"updated_at":"2013-02-11T10:57:12Z","icon_urls":{"small":"/icons/small/missing.png","med":"/icons/med/missing.png","big":"/icons/big/missing.png"}},{"created_at":"2013-02-11T10:57:12Z","description":null,"foursquare_icon":null,"foursquare_id":null,"group":"sleep_resting_cities","icon_content_type":null,"icon_file_name":null,"icon_file_size":null,"icon_update_at":null,"id":91,"is_route":null,"name":"Ciudades de descanso","name_en":null,"name_eu":null,"slug":null,"supercategory_id":6,"updated_at":"2013-02-11T10:57:12Z","icon_urls":{"small":"/icons/small/missing.png","med":"/icons/med/missing.png","big":"/icons/big/missing.png"}},{"created_at":"2013-02-11T10:57:12Z","description":null,"foursquare_icon":null,"foursquare_id":null,"group":"do","icon_content_type":null,"icon_file_name":null,"icon_file_size":null,"icon_update_at":null,"id":92,"is_route":null,"name":"Teatros","name_en":null,"name_eu":null,"slug":null,"supercategory_id":2,"updated_at":"2013-02-11T10:57:12Z","icon_urls":{"small":"/icons/small/missing.png","med":"/icons/med/missing.png","big":"/icons/big/missing.png"}},{"created_at":"2013-02-11T10:57:13Z","description":null,"foursquare_icon":null,"foursquare_id":null,"group":"do","icon_content_type":null,"icon_file_name":null,"icon_file_size":null,"icon_update_at":null,"id":93,"is_route":null,"name":"Hamman Turco","name_en":null,"name_eu":null,"slug":null,"supercategory_id":3,"updated_at":"2013-02-11T10:57:13Z","icon_urls":{"small":"/icons/small/missing.png","med":"/icons/med/missing.png","big":"/icons/big/missing.png"}},{"created_at":"2013-02-11T10:57:12Z","description":null,"foursquare_icon":null,"foursquare_id":null,"group":"do","icon_content_type":null,"icon_file_name":null,"icon_file_size":null,"icon_update_at":null,"id":94,"is_route":null,"name":"Espect\u00e1culos","name_en":null,"name_eu":null,"slug":null,"supercategory_id":5,"updated_at":"2013-02-11T10:57:12Z","icon_urls":{"small":"/icons/small/missing.png","med":"/icons/med/missing.png","big":"/icons/big/missing.png"}},{"created_at":"2013-02-11T10:57:12Z","description":null,"foursquare_icon":null,"foursquare_id":null,"group":"tosee","icon_content_type":null,"icon_file_name":null,"icon_file_size":null,"icon_update_at":null,"id":95,"is_route":null,"name":"Embajadas","name_en":null,"name_eu":null,"slug":null,"supercategory_id":8,"updated_at":"2013-02-11T10:57:12Z","icon_urls":{"small":"/icons/small/missing.png","med":"/icons/med/missing.png","big":"/icons/big/missing.png"}},{"created_at":"2013-02-11T10:57:12Z","description":null,"foursquare_icon":null,"foursquare_id":null,"group":"tosee","icon_content_type":null,"icon_file_name":null,"icon_file_size":null,"icon_update_at":null,"id":96,"is_route":null,"name":"Consulados","name_en":null,"name_eu":null,"slug":null,"supercategory_id":8,"updated_at":"2013-02-11T10:57:12Z","icon_urls":{"small":"/icons/small/missing.png","med":"/icons/med/missing.png","big":"/icons/big/missing.png"}},{"created_at":"2013-02-11T10:57:12Z","description":null,"foursquare_icon":null,"foursquare_id":null,"group":"tosee","icon_content_type":null,"icon_file_name":null,"icon_file_size":null,"icon_update_at":null,"id":97,"is_route":null,"name":"Comisar\u00edas","name_en":null,"name_eu":null,"slug":null,"supercategory_id":8,"updated_at":"2013-02-11T10:57:12Z","icon_urls":{"small":"/icons/small/missing.png","med":"/icons/med/missing.png","big":"/icons/big/missing.png"}},{"created_at":"2013-02-11T10:57:12Z","description":null,"foursquare_icon":null,"foursquare_id":null,"group":"tosee","icon_content_type":null,"icon_file_name":null,"icon_file_size":null,"icon_update_at":null,"id":98,"is_route":null,"name":"Estaciones de Bomberos","name_en":null,"name_eu":null,"slug":null,"supercategory_id":8,"updated_at":"2013-02-11T10:57:12Z","icon_urls":{"small":"/icons/small/missing.png","med":"/icons/med/missing.png","big":"/icons/big/missing.png"}},{"created_at":"2013-02-11T10:57:12Z","description":null,"foursquare_icon":null,"foursquare_id":null,"group":"tosee","icon_content_type":null,"icon_file_name":null,"icon_file_size":null,"icon_update_at":null,"id":99,"is_route":null,"name":"Hospitales","name_en":null,"name_eu":null,"slug":null,"supercategory_id":8,"updated_at":"2013-02-11T10:57:12Z","icon_urls":{"small":"/icons/small/missing.png","med":"/icons/med/missing.png","big":"/icons/big/missing.png"}},{"created_at":"2013-02-11T10:57:12Z","description":null,"foursquare_icon":null,"foursquare_id":null,"group":"tosee","icon_content_type":null,"icon_file_name":null,"icon_file_size":null,"icon_update_at":null,"id":100,"is_route":null,"name":"Centros de Salud","name_en":null,"name_eu":null,"slug":null,"supercategory_id":8,"updated_at":"2013-02-11T10:57:12Z","icon_urls":{"small":"/icons/small/missing.png","med":"/icons/med/missing.png","big":"/icons/big/missing.png"}},{"created_at":"2013-02-11T10:57:12Z","description":null,"foursquare_icon":null,"foursquare_id":null,"group":"tosee","icon_content_type":null,"icon_file_name":null,"icon_file_size":null,"icon_update_at":null,"id":101,"is_route":null,"name":"Informaci\u00f3n Tur\u00edstica","name_en":null,"name_eu":null,"slug":null,"supercategory_id":8,"updated_at":"2013-02-11T10:57:12Z","icon_urls":{"small":"/icons/small/missing.png","med":"/icons/med/missing.png","big":"/icons/big/missing.png"}},{"created_at":"2013-02-11T10:57:13Z","description":null,"foursquare_icon":null,"foursquare_id":null,"group":"do","icon_content_type":null,"icon_file_name":null,"icon_file_size":null,"icon_update_at":null,"id":102,"is_route":null,"name":"Mercados","name_en":null,"name_eu":null,"slug":null,"supercategory_id":3,"updated_at":"2013-02-11T10:57:13Z","icon_urls":{"small":"/icons/small/missing.png","med":"/icons/med/missing.png","big":"/icons/big/missing.png"}},{"created_at":"2013-02-11T10:57:13Z","description":null,"foursquare_icon":null,"foursquare_id":null,"group":"tosee","icon_content_type":null,"icon_file_name":null,"icon_file_size":null,"icon_update_at":null,"id":103,"is_route":null,"name":"Ruinas","name_en":null,"name_eu":null,"slug":null,"supercategory_id":1,"updated_at":"2013-02-11T10:57:13Z","icon_urls":{"small":"/icons/small/missing.png","med":"/icons/med/missing.png","big":"/icons/big/missing.png"}},{"created_at":"2013-02-11T10:57:13Z","description":null,"foursquare_icon":null,"foursquare_id":null,"group":"do","icon_content_type":null,"icon_file_name":null,"icon_file_size":null,"icon_update_at":null,"id":104,"is_route":null,"name":"Zonas Recreativas","name_en":null,"name_eu":null,"slug":null,"supercategory_id":3,"updated_at":"2013-02-11T10:57:13Z","icon_urls":{"small":"/icons/small/missing.png","med":"/icons/med/missing.png","big":"/icons/big/missing.png"}},{"created_at":"2013-02-11T10:57:12Z","description":null,"foursquare_icon":null,"foursquare_id":null,"group":"do","icon_content_type":null,"icon_file_name":null,"icon_file_size":null,"icon_update_at":null,"id":105,"is_route":null,"name":"H\u00edpica","name_en":null,"name_eu":null,"slug":null,"supercategory_id":4,"updated_at":"2013-02-11T10:57:12Z","icon_urls":{"small":"/icons/small/missing.png","med":"/icons/med/missing.png","big":"/icons/big/missing.png"}},{"created_at":"2013-02-11T10:57:12Z","description":null,"foursquare_icon":null,"foursquare_id":null,"group":"sleep_resorts","icon_content_type":null,"icon_file_name":null,"icon_file_size":null,"icon_update_at":null,"id":106,"is_route":null,"name":"Resorts","name_en":null,"name_eu":null,"slug":null,"supercategory_id":6,"updated_at":"2013-02-11T10:57:12Z","icon_urls":{"small":"/icons/small/missing.png","med":"/icons/med/missing.png","big":"/icons/big/missing.png"}},{"created_at":"2013-02-11T10:57:13Z","description":null,"foursquare_icon":null,"foursquare_id":null,"group":"tosee","icon_content_type":null,"icon_file_name":null,"icon_file_size":null,"icon_update_at":null,"id":108,"is_route":null,"name":"Volcanes","name_en":null,"name_eu":null,"slug":null,"supercategory_id":1,"updated_at":"2013-02-11T10:57:13Z","icon_urls":{"small":"/icons/small/missing.png","med":"/icons/med/missing.png","big":"/icons/big/missing.png"}},{"created_at":"2013-02-11T10:57:13Z","description":null,"foursquare_icon":null,"foursquare_id":null,"group":"tosee","icon_content_type":null,"icon_file_name":null,"icon_file_size":null,"icon_update_at":null,"id":109,"is_route":null,"name":"Ca\u00f1ones","name_en":null,"name_eu":null,"slug":null,"supercategory_id":1,"updated_at":"2013-02-11T10:57:13Z","icon_urls":{"small":"/icons/small/missing.png","med":"/icons/med/missing.png","big":"/icons/big/missing.png"}},{"created_at":"2013-02-11T10:57:13Z","description":null,"foursquare_icon":null,"foursquare_id":null,"group":"tosee","icon_content_type":null,"icon_file_name":null,"icon_file_size":null,"icon_update_at":null,"id":110,"is_route":null,"name":"Puertos","name_en":null,"name_eu":null,"slug":null,"supercategory_id":1,"updated_at":"2013-02-11T10:57:13Z","icon_urls":{"small":"/icons/small/missing.png","med":"/icons/med/missing.png","big":"/icons/big/missing.png"}},{"created_at":"2013-02-11T10:57:13Z","description":null,"foursquare_icon":null,"foursquare_id":null,"group":"tosee","icon_content_type":null,"icon_file_name":null,"icon_file_size":null,"icon_update_at":null,"id":111,"is_route":null,"name":"Calas","name_en":null,"name_eu":null,"slug":null,"supercategory_id":1,"updated_at":"2013-02-11T10:57:13Z","icon_urls":{"small":"/icons/small/missing.png","med":"/icons/med/missing.png","big":"/icons/big/missing.png"}},{"created_at":"2013-02-11T10:57:13Z","description":null,"foursquare_icon":null,"foursquare_id":null,"group":"tosee","icon_content_type":null,"icon_file_name":null,"icon_file_size":null,"icon_update_at":null,"id":112,"is_route":null,"name":"Pueblos","name_en":null,"name_eu":null,"slug":null,"supercategory_id":1,"updated_at":"2013-02-11T10:57:13Z","icon_urls":{"small":"/icons/small/missing.png","med":"/icons/med/missing.png","big":"/icons/big/missing.png"}},{"created_at":"2013-02-11T10:57:13Z","description":null,"foursquare_icon":null,"foursquare_id":null,"group":"tosee","icon_content_type":null,"icon_file_name":null,"icon_file_size":null,"icon_update_at":null,"id":113,"is_route":null,"name":"Fiordos","name_en":null,"name_eu":null,"slug":null,"supercategory_id":1,"updated_at":"2013-02-11T10:57:13Z","icon_urls":{"small":"/icons/small/missing.png","med":"/icons/med/missing.png","big":"/icons/big/missing.png"}},{"created_at":"2013-02-11T10:57:13Z","description":null,"foursquare_icon":null,"foursquare_id":null,"group":"tosee","icon_content_type":null,"icon_file_name":null,"icon_file_size":null,"icon_update_at":null,"id":114,"is_route":null,"name":"Carreteras","name_en":null,"name_eu":null,"slug":null,"supercategory_id":1,"updated_at":"2013-02-11T10:57:13Z","icon_urls":{"small":"/icons/small/missing.png","med":"/icons/med/missing.png","big":"/icons/big/missing.png"}},{"created_at":"2013-02-11T10:57:13Z","description":null,"foursquare_icon":null,"foursquare_id":null,"group":"tosee","icon_content_type":null,"icon_file_name":null,"icon_file_size":null,"icon_update_at":null,"id":115,"is_route":null,"name":"Ciudades","name_en":null,"name_eu":null,"slug":null,"supercategory_id":1,"updated_at":"2013-02-11T10:57:13Z","icon_urls":{"small":"/icons/small/missing.png","med":"/icons/med/missing.png","big":"/icons/big/missing.png"}},{"created_at":"2013-02-11T10:57:12Z","description":null,"foursquare_icon":null,"foursquare_id":null,"group":"tosee","icon_content_type":null,"icon_file_name":null,"icon_file_size":null,"icon_update_at":null,"id":116,"is_route":null,"name":"Cementerios","name_en":null,"name_eu":null,"slug":null,"supercategory_id":2,"updated_at":"2013-02-11T10:57:12Z","icon_urls":{"small":"/icons/small/missing.png","med":"/icons/med/missing.png","big":"/icons/big/missing.png"}},{"created_at":"2013-02-11T10:57:13Z","description":null,"foursquare_icon":null,"foursquare_id":null,"group":"tosee","icon_content_type":null,"icon_file_name":null,"icon_file_size":null,"icon_update_at":null,"id":118,"is_route":null,"name":"Selva","name_en":null,"name_eu":null,"slug":null,"supercategory_id":1,"updated_at":"2013-02-11T10:57:13Z","icon_urls":{"small":"/icons/small/missing.png","med":"/icons/med/missing.png","big":"/icons/big/missing.png"}},{"created_at":"2013-02-11T10:57:13Z","description":null,"foursquare_icon":null,"foursquare_id":null,"group":"tosee","icon_content_type":null,"icon_file_name":null,"icon_file_size":null,"icon_update_at":null,"id":119,"is_route":null,"name":"Patios","name_en":null,"name_eu":null,"slug":null,"supercategory_id":1,"updated_at":"2013-02-11T10:57:13Z","icon_urls":{"small":"/icons/small/missing.png","med":"/icons/med/missing.png","big":"/icons/big/missing.png"}},{"created_at":"2013-02-11T10:57:12Z","description":null,"foursquare_icon":null,"foursquare_id":null,"group":"tosee","icon_content_type":null,"icon_file_name":null,"icon_file_size":null,"icon_update_at":null,"id":120,"is_route":null,"name":"Mezquitas","name_en":null,"name_eu":null,"slug":null,"supercategory_id":2,"updated_at":"2013-02-11T10:57:12Z","icon_urls":{"small":"/icons/small/missing.png","med":"/icons/med/missing.png","big":"/icons/big/missing.png"}},{"created_at":"2013-02-11T10:57:13Z","description":null,"foursquare_icon":null,"foursquare_id":null,"group":"do","icon_content_type":null,"icon_file_name":null,"icon_file_size":null,"icon_update_at":null,"id":121,"is_route":null,"name":"Mercadillos","name_en":null,"name_eu":null,"slug":null,"supercategory_id":3,"updated_at":"2013-02-11T10:57:13Z","icon_urls":{"small":"/icons/small/missing.png","med":"/icons/med/missing.png","big":"/icons/big/missing.png"}},{"created_at":"2013-02-11T10:57:12Z","description":null,"foursquare_icon":null,"foursquare_id":null,"group":"tosee","icon_content_type":null,"icon_file_name":null,"icon_file_size":null,"icon_update_at":null,"id":122,"is_route":null,"name":"Universidades","name_en":null,"name_eu":null,"slug":null,"supercategory_id":2,"updated_at":"2013-02-11T10:57:12Z","icon_urls":{"small":"/icons/small/missing.png","med":"/icons/med/missing.png","big":"/icons/big/missing.png"}},{"created_at":"2013-02-11T10:57:12Z","description":null,"foursquare_icon":null,"foursquare_id":null,"group":"sleep_hostels","icon_content_type":null,"icon_file_name":null,"icon_file_size":null,"icon_update_at":null,"id":123,"is_route":null,"name":"Albergues","name_en":null,"name_eu":null,"slug":null,"supercategory_id":6,"updated_at":"2013-02-11T10:57:12Z","icon_urls":{"small":"/icons/small/missing.png","med":"/icons/med/missing.png","big":"/icons/big/missing.png"}},{"created_at":"2013-02-11T10:57:12Z","description":null,"foursquare_icon":null,"foursquare_id":null,"group":"sleep_motels","icon_content_type":null,"icon_file_name":null,"icon_file_size":null,"icon_update_at":null,"id":124,"is_route":null,"name":"Moteles","name_en":null,"name_eu":null,"slug":null,"supercategory_id":6,"updated_at":"2013-02-11T10:57:12Z","icon_urls":{"small":"/icons/small/missing.png","med":"/icons/med/missing.png","big":"/icons/big/missing.png"}},{"created_at":"2013-02-11T10:57:13Z","description":null,"foursquare_icon":null,"foursquare_id":null,"group":"tosee","icon_content_type":null,"icon_file_name":null,"icon_file_size":null,"icon_update_at":null,"id":125,"is_route":null,"name":"Bah\u00edas","name_en":null,"name_eu":null,"slug":null,"supercategory_id":1,"updated_at":"2013-02-11T10:57:13Z","icon_urls":{"small":"/icons/small/missing.png","med":"/icons/med/missing.png","big":"/icons/big/missing.png"}},{"created_at":"2013-02-11T10:57:13Z","description":null,"foursquare_icon":null,"foursquare_id":null,"group":"tosee","icon_content_type":null,"icon_file_name":null,"icon_file_size":null,"icon_update_at":null,"id":126,"is_route":null,"name":"Valles","name_en":null,"name_eu":null,"slug":null,"supercategory_id":1,"updated_at":"2013-02-11T10:57:13Z","icon_urls":{"small":"/icons/small/missing.png","med":"/icons/med/missing.png","big":"/icons/big/missing.png"}},{"created_at":"2013-02-11T10:57:13Z","description":null,"foursquare_icon":null,"foursquare_id":null,"group":"tosee","icon_content_type":null,"icon_file_name":null,"icon_file_size":null,"icon_update_at":null,"id":127,"is_route":null,"name":"Sitios ins\u00f3litos","name_en":null,"name_eu":null,"slug":null,"supercategory_id":1,"updated_at":"2013-02-11T10:57:13Z","icon_urls":{"small":"/icons/small/missing.png","med":"/icons/med/missing.png","big":"/icons/big/missing.png"}},{"created_at":"2013-02-11T10:57:13Z","description":null,"foursquare_icon":null,"foursquare_id":null,"group":"tosee","icon_content_type":null,"icon_file_name":null,"icon_file_size":null,"icon_update_at":null,"id":128,"is_route":null,"name":"Plazas","name_en":null,"name_eu":null,"slug":null,"supercategory_id":1,"updated_at":"2013-02-11T10:57:13Z","icon_urls":{"small":"/icons/small/missing.png","med":"/icons/med/missing.png","big":"/icons/big/missing.png"}},{"created_at":"2013-02-11T10:57:13Z","description":null,"foursquare_icon":null,"foursquare_id":null,"group":"tosee","icon_content_type":null,"icon_file_name":null,"icon_file_size":null,"icon_update_at":null,"id":129,"is_route":null,"name":"Calles","name_en":null,"name_eu":null,"slug":null,"supercategory_id":1,"updated_at":"2013-02-11T10:57:13Z","icon_urls":{"small":"/icons/small/missing.png","med":"/icons/med/missing.png","big":"/icons/big/missing.png"}},{"created_at":"2013-02-11T10:57:13Z","description":null,"foursquare_icon":null,"foursquare_id":null,"group":"tosee","icon_content_type":null,"icon_file_name":null,"icon_file_size":null,"icon_update_at":null,"id":130,"is_route":null,"name":"Pueblos de vacaciones","name_en":null,"name_eu":null,"slug":null,"supercategory_id":1,"updated_at":"2013-02-11T10:57:13Z","icon_urls":{"small":"/icons/small/missing.png","med":"/icons/med/missing.png","big":"/icons/big/missing.png"}},{"created_at":"2013-02-11T10:57:12Z","description":null,"foursquare_icon":null,"foursquare_id":null,"group":"tosee","icon_content_type":null,"icon_file_name":null,"icon_file_size":null,"icon_update_at":null,"id":131,"is_route":null,"name":"Abad\u00edas","name_en":null,"name_eu":null,"slug":null,"supercategory_id":2,"updated_at":"2013-02-11T10:57:12Z","icon_urls":{"small":"/icons/small/missing.png","med":"/icons/med/missing.png","big":"/icons/big/missing.png"}},{"created_at":"2013-02-11T10:57:12Z","description":null,"foursquare_icon":null,"foursquare_id":null,"group":"tosee","icon_content_type":null,"icon_file_name":null,"icon_file_size":null,"icon_update_at":null,"id":132,"is_route":null,"name":"Ciudadelas","name_en":null,"name_eu":null,"slug":null,"supercategory_id":2,"updated_at":"2013-02-11T10:57:12Z","icon_urls":{"small":"/icons/small/missing.png","med":"/icons/med/missing.png","big":"/icons/big/missing.png"}},{"created_at":"2013-02-11T10:57:12Z","description":null,"foursquare_icon":null,"foursquare_id":null,"group":"tosee","icon_content_type":null,"icon_file_name":null,"icon_file_size":null,"icon_update_at":null,"id":133,"is_route":null,"name":"Ksars","name_en":null,"name_eu":null,"slug":null,"supercategory_id":2,"updated_at":"2013-02-11T10:57:12Z","icon_urls":{"small":"/icons/small/missing.png","med":"/icons/med/missing.png","big":"/icons/big/missing.png"}},{"created_at":"2013-02-11T10:57:12Z","description":null,"foursquare_icon":null,"foursquare_id":null,"group":"tosee","icon_content_type":null,"icon_file_name":null,"icon_file_size":null,"icon_update_at":null,"id":134,"is_route":null,"name":"Sinagogas","name_en":null,"name_eu":null,"slug":null,"supercategory_id":2,"updated_at":"2013-02-11T10:57:12Z","icon_urls":{"small":"/icons/small/missing.png","med":"/icons/med/missing.png","big":"/icons/big/missing.png"}},{"created_at":"2013-02-11T10:57:13Z","description":null,"foursquare_icon":null,"foursquare_id":null,"group":"tosee","icon_content_type":null,"icon_file_name":null,"icon_file_size":null,"icon_update_at":null,"id":135,"is_route":null,"name":"Charcas","name_en":null,"name_eu":null,"slug":null,"supercategory_id":1,"updated_at":"2013-02-11T10:57:13Z","icon_urls":{"small":"/icons/small/missing.png","med":"/icons/med/missing.png","big":"/icons/big/missing.png"}},{"created_at":"2013-02-11T10:57:12Z","description":null,"foursquare_icon":null,"foursquare_id":null,"group":"tosee","icon_content_type":null,"icon_file_name":null,"icon_file_size":null,"icon_update_at":null,"id":136,"is_route":null,"name":"Templos","name_en":null,"name_eu":null,"slug":null,"supercategory_id":2,"updated_at":"2013-02-11T10:57:12Z","icon_urls":{"small":"/icons/small/missing.png","med":"/icons/med/missing.png","big":"/icons/big/missing.png"}},{"created_at":"2013-02-11T10:57:12Z","description":null,"foursquare_icon":null,"foursquare_id":null,"group":"tosee","icon_content_type":null,"icon_file_name":null,"icon_file_size":null,"icon_update_at":null,"id":137,"is_route":null,"name":"Yacimientos Arqueol\u00f3gicos","name_en":null,"name_eu":null,"slug":null,"supercategory_id":2,"updated_at":"2013-02-11T10:57:12Z","icon_urls":{"small":"/icons/small/missing.png","med":"/icons/med/missing.png","big":"/icons/big/missing.png"}},{"created_at":"2013-02-11T10:57:13Z","description":null,"foursquare_icon":null,"foursquare_id":null,"group":"tosee","icon_content_type":null,"icon_file_name":null,"icon_file_size":null,"icon_update_at":null,"id":138,"is_route":null,"name":"Desiertos","name_en":null,"name_eu":null,"slug":null,"supercategory_id":1,"updated_at":"2013-02-11T10:57:13Z","icon_urls":{"small":"/icons/small/missing.png","med":"/icons/med/missing.png","big":"/icons/big/missing.png"}},{"created_at":"2013-02-11T10:57:12Z","description":null,"foursquare_icon":null,"foursquare_id":null,"group":"sleep_pension","icon_content_type":null,"icon_file_name":null,"icon_file_size":null,"icon_update_at":null,"id":139,"is_route":null,"name":"Pensiones","name_en":null,"name_eu":null,"slug":null,"supercategory_id":6,"updated_at":"2013-02-11T10:57:12Z","icon_urls":{"small":"/icons/small/missing.png","med":"/icons/med/missing.png","big":"/icons/big/missing.png"}},{"created_at":"2013-02-11T10:57:13Z","description":null,"foursquare_icon":null,"foursquare_id":null,"group":"do","icon_content_type":null,"icon_file_name":null,"icon_file_size":null,"icon_update_at":null,"id":141,"is_route":null,"name":"Bodegas","name_en":null,"name_eu":null,"slug":null,"supercategory_id":3,"updated_at":"2013-02-11T10:57:13Z","icon_urls":{"small":"/icons/small/missing.png","med":"/icons/med/missing.png","big":"/icons/big/missing.png"}}]